{
  "J1": ["Kylian Mbappé", "Erling Haaland", "Lionel Messi", "Harry Kane", "Mikel Oyarzabal"],
  "J2": ["Cristiano Ronaldo", "Lamine Yamal", "Jude Bellingham", "Vinícius Jr.", "Lautaro Martínez"],
  "J3": ["Luis Díaz", "Darwin Núñez", "Ousmane Dembélé", "Jonathan David", "Kai Havertz"],
  "J4": ["Raphinha", "Donyell Malen", "Bukayo Saka", "Leroy Sané", "Arda Güler"],
  "J5": ["Julian Alvarez", "Ferran Torres", "Kevin De Bruyne", "Romelu Lukaku", "Rafael Leao"],
  "J6": ["Alexander Isak", "Viktor Gyökeres", "Alexander Sørloth", "Antoine Semenyo", "Mohamed Salah"]
}